pyhocon/__init__.py
pyhocon/config_parser.py
pyhocon/config_tree.py
pyhocon/converter.py
pyhocon/exceptions.py
pyhocon/period_parser.py
pyhocon/period_serializer.py
pyhocon/tool.py
dd_pyhocon-0.3.61.dist-info/LICENSE
dd_pyhocon-0.3.61.dist-info/METADATA
dd_pyhocon-0.3.61.dist-info/WHEEL
dd_pyhocon-0.3.61.dist-info/entry_points.txt
dd_pyhocon-0.3.61.dist-info/top_level.txt
dd_pyhocon-0.3.61.dist-info/RECORD
