Metadata-Version: 2.1
Name: dd-pyhocon
Version: 0.3.61
Summary: HOCON parser for Python
Home-page: http://github.com/chimpler/pyhocon/
Author: Francois Dang Ngoc
Author-email: francois.dangngoc@gmail.com
License: Apache License 2.0
Keywords: hocon parser
Classifier: License :: OSI Approved :: Apache Software License
Classifier: Topic :: Software Development :: Libraries :: Python Modules
Classifier: Programming Language :: Python
Classifier: Programming Language :: Python :: 2
Classifier: Programming Language :: Python :: 2.7
Classifier: Programming Language :: Python :: 3
Classifier: Programming Language :: Python :: 3.4
Classifier: Programming Language :: Python :: 3.5
Classifier: Programming Language :: Python :: 3.6
Classifier: Programming Language :: Python :: 3.7
Classifier: Programming Language :: Python :: 3.8
Classifier: Programming Language :: Python :: 3.9
License-File: LICENSE
Requires-Dist: pyparsing (~=2.0) ; python_version < "3.0"
Requires-Dist: pyparsing (<4,>=2) ; python_version >= "3.0"
Provides-Extra: duration
Requires-Dist: python-dateutil (>=2.8.0) ; extra == 'duration'
